{"version":3,"kind":"Notebook","sha256":"c63c2635d84d85da96d4a7192fb78df41083cf06bb618c11fe37a82fee618b23","slug":"database","location":"/1-introduction/database.ipynb","dependencies":[],"frontmatter":{"title":"Chapter 1: What Is a Database?","content_includes_title":false,"kernelspec":{"name":"python3","display_name":"Python 3 (ipykernel)","language":"python"},"github":"https://github.com/dudaspm/Introduction_to_Databases","keywords":["sql","jupyter"],"source_url":"https://github.com/dudaspm/Introduction_to_Databases/blob/main/1-introduction/database.ipynb","edit_url":"https://github.com/dudaspm/Introduction_to_Databases/edit/main/1-introduction/database.ipynb","exports":[{"format":"ipynb","filename":"database.ipynb","url":"/database-ed75fcbc2f4ae302455f8666751f42ac.ipynb"}]},"widgets":{},"mdast":{"type":"root","children":[{"type":"block","kind":"notebook-content","children":[{"type":"admonition","kind":"important","children":[{"type":"admonitionTitle","children":[{"type":"text","value":"Objective","position":{"start":{"line":2,"column":1},"end":{"line":2,"column":1}},"key":"IKKNapQpSH"}],"key":"ky0pJmergD"},{"type":"heading","depth":2,"position":{"start":{"line":3,"column":1},"end":{"line":3,"column":1}},"children":[{"type":"text","value":"Learning Objectives","position":{"start":{"line":3,"column":1},"end":{"line":3,"column":1}},"key":"N66EfNHpdd"}],"identifier":"learning-objectives","label":"Learning Objectives","html_id":"learning-objectives","implicit":true,"key":"JJLsXY7GRe"},{"type":"paragraph","position":{"start":{"line":5,"column":1},"end":{"line":5,"column":1}},"children":[{"type":"text","value":"By the end of this chapter, you should be able to:","position":{"start":{"line":5,"column":1},"end":{"line":5,"column":1}},"key":"XcHBUOHEwz"}],"key":"iULs3vMpQh"},{"type":"list","ordered":true,"start":1,"spread":false,"position":{"start":{"line":7,"column":1},"end":{"line":11,"column":1}},"children":[{"type":"listItem","spread":true,"position":{"start":{"line":7,"column":1},"end":{"line":7,"column":1}},"children":[{"type":"paragraph","children":[{"type":"text","value":"Describe what a database is.","position":{"start":{"line":7,"column":1},"end":{"line":7,"column":1}},"key":"JbuysRlIS6"}],"key":"Xm7EoUHiw3"}],"key":"oMxvJBZCLz"},{"type":"listItem","spread":true,"position":{"start":{"line":8,"column":1},"end":{"line":8,"column":1}},"children":[{"type":"paragraph","children":[{"type":"text","value":"Explain why databases are useful in organizations.","position":{"start":{"line":8,"column":1},"end":{"line":8,"column":1}},"key":"tivIvRj5z3"}],"key":"SPC9iK7kgl"}],"key":"iHLVXDXa4n"},{"type":"listItem","spread":true,"position":{"start":{"line":9,"column":1},"end":{"line":9,"column":1}},"children":[{"type":"paragraph","children":[{"type":"text","value":"Distinguish between data, information, databases, and database management systems.","position":{"start":{"line":9,"column":1},"end":{"line":9,"column":1}},"key":"Q4DiLqGjEG"}],"key":"BtG90HFlN9"}],"key":"ycmATg7vPv"},{"type":"listItem","spread":true,"position":{"start":{"line":10,"column":1},"end":{"line":10,"column":1}},"children":[{"type":"paragraph","children":[{"type":"text","value":"Compare a spreadsheet-based approach with a database-based approach.","position":{"start":{"line":10,"column":1},"end":{"line":10,"column":1}},"key":"NT6ND0vQzJ"}],"key":"I6DxE8YKgH"}],"key":"ZePvCQ93GN"},{"type":"listItem","spread":true,"position":{"start":{"line":11,"column":1},"end":{"line":11,"column":1}},"children":[{"type":"paragraph","children":[{"type":"text","value":"Use a small SQLite database to store and retrieve data.","position":{"start":{"line":11,"column":1},"end":{"line":11,"column":1}},"key":"wURjob5MbF"}],"key":"ustUCTJVNd"}],"key":"P2CdF1TaWy"}],"key":"AwCMYdCrfZ"}],"key":"cfHhKGYjxZ"}],"key":"UV4Wnkekn3"},{"type":"block","kind":"notebook-content","children":[{"type":"heading","depth":2,"position":{"start":{"line":1,"column":1},"end":{"line":1,"column":1}},"children":[{"type":"text","value":"1.1 Why Study Databases?","position":{"start":{"line":1,"column":1},"end":{"line":1,"column":1}},"key":"k2PtGqEkUh"}],"identifier":"id-1-1-why-study-databases","label":"1.1 Why Study Databases?","html_id":"id-1-1-why-study-databases","implicit":true,"key":"KRLK5Ud7HP"},{"type":"paragraph","position":{"start":{"line":3,"column":1},"end":{"line":3,"column":1}},"children":[{"type":"text","value":"Every organization depends on data. Colleges store student records. Hospitals track patients and appointments. Retail companies manage customers, products, and orders. Manufacturers track inventory, suppliers, machines, and production schedules.","position":{"start":{"line":3,"column":1},"end":{"line":3,"column":1}},"key":"pd3mExvx5f"}],"key":"IXzGl0JItl"},{"type":"paragraph","position":{"start":{"line":5,"column":1},"end":{"line":5,"column":1}},"children":[{"type":"text","value":"A ","position":{"start":{"line":5,"column":1},"end":{"line":5,"column":1}},"key":"bXaoskTd20"},{"type":"strong","position":{"start":{"line":5,"column":1},"end":{"line":5,"column":1}},"children":[{"type":"text","value":"database","position":{"start":{"line":5,"column":1},"end":{"line":5,"column":1}},"key":"CtOLeZvV0j"}],"key":"Z6s9QKiBlQ"},{"type":"text","value":" is a structured collection of related data. Databases help organizations store, organize, search, update, protect, and share data.","position":{"start":{"line":5,"column":1},"end":{"line":5,"column":1}},"key":"iCeBoMK3rC"}],"key":"oGHqTvjGlt"},{"type":"paragraph","position":{"start":{"line":7,"column":1},"end":{"line":7,"column":1}},"children":[{"type":"text","value":"Databases matter because they allow people to answer important questions, such as:","position":{"start":{"line":7,"column":1},"end":{"line":7,"column":1}},"key":"bWc1kqtkje"}],"key":"VhpsbazUAp"},{"type":"list","ordered":false,"spread":false,"position":{"start":{"line":9,"column":1},"end":{"line":14,"column":1}},"children":[{"type":"listItem","spread":true,"position":{"start":{"line":9,"column":1},"end":{"line":9,"column":1}},"children":[{"type":"paragraph","children":[{"type":"text","value":"Which students are enrolled in a course?","position":{"start":{"line":9,"column":1},"end":{"line":9,"column":1}},"key":"y2B5x2EIIE"}],"key":"Tr2p7RcjoU"}],"key":"PQyJxMQF6a"},{"type":"listItem","spread":true,"position":{"start":{"line":10,"column":1},"end":{"line":10,"column":1}},"children":[{"type":"paragraph","children":[{"type":"text","value":"Which customers placed orders last month?","position":{"start":{"line":10,"column":1},"end":{"line":10,"column":1}},"key":"MEEfLyLJag"}],"key":"c4wDRbp4dD"}],"key":"D7irF0Flcy"},{"type":"listItem","spread":true,"position":{"start":{"line":11,"column":1},"end":{"line":11,"column":1}},"children":[{"type":"paragraph","children":[{"type":"text","value":"Which products are low in inventory?","position":{"start":{"line":11,"column":1},"end":{"line":11,"column":1}},"key":"niNHgJ94VZ"}],"key":"ppqBnQyYDr"}],"key":"llQ5L7WRxU"},{"type":"listItem","spread":true,"position":{"start":{"line":12,"column":1},"end":{"line":12,"column":1}},"children":[{"type":"paragraph","children":[{"type":"text","value":"Which employees worked on a project?","position":{"start":{"line":12,"column":1},"end":{"line":12,"column":1}},"key":"YFZV6ULSkp"}],"key":"DhFNVvbZMD"}],"key":"Ol32a3glW6"},{"type":"listItem","spread":true,"position":{"start":{"line":13,"column":1},"end":{"line":14,"column":1}},"children":[{"type":"paragraph","children":[{"type":"text","value":"Which machines need maintenance?","position":{"start":{"line":13,"column":1},"end":{"line":13,"column":1}},"key":"KOVop6NsTc"}],"key":"vjVwvGGFMc"}],"key":"Kv9OqszG9Z"}],"key":"IlRczRJIGX"},{"type":"paragraph","position":{"start":{"line":15,"column":1},"end":{"line":15,"column":1}},"children":[{"type":"text","value":"In this book, we will focus mostly on ","position":{"start":{"line":15,"column":1},"end":{"line":15,"column":1}},"key":"xwlGNWfzar"},{"type":"strong","position":{"start":{"line":15,"column":1},"end":{"line":15,"column":1}},"children":[{"type":"text","value":"relational databases","position":{"start":{"line":15,"column":1},"end":{"line":15,"column":1}},"key":"N9R5U0zp1x"}],"key":"XznEQg78Xm"},{"type":"text","value":" and ","position":{"start":{"line":15,"column":1},"end":{"line":15,"column":1}},"key":"avCI7lwzQq"},{"type":"strong","position":{"start":{"line":15,"column":1},"end":{"line":15,"column":1}},"children":[{"type":"text","value":"SQL","position":{"start":{"line":15,"column":1},"end":{"line":15,"column":1}},"key":"EUZijhHcOz"}],"key":"e0y4AxZbSC"},{"type":"text","value":", which is the language commonly used to work with relational databases.","position":{"start":{"line":15,"column":1},"end":{"line":15,"column":1}},"key":"bLiVxqf9kW"}],"key":"Ma13OooipV"}],"key":"HZu1z5ugbW"},{"type":"block","kind":"notebook-content","children":[{"type":"heading","depth":2,"position":{"start":{"line":1,"column":1},"end":{"line":1,"column":1}},"children":[{"type":"text","value":"1.2 Data vs. Information","position":{"start":{"line":1,"column":1},"end":{"line":1,"column":1}},"key":"nT5tYUaXAC"}],"identifier":"id-1-2-data-vs-information","label":"1.2 Data vs. Information","html_id":"id-1-2-data-vs-information","implicit":true,"key":"UZ28T63SSk"},{"type":"paragraph","position":{"start":{"line":3,"column":1},"end":{"line":3,"column":1}},"children":[{"type":"text","value":"Although people often use the words interchangeably, ","position":{"start":{"line":3,"column":1},"end":{"line":3,"column":1}},"key":"hIoTQxU3AY"},{"type":"strong","position":{"start":{"line":3,"column":1},"end":{"line":3,"column":1}},"children":[{"type":"text","value":"data","position":{"start":{"line":3,"column":1},"end":{"line":3,"column":1}},"key":"cjEfLm7aHO"}],"key":"NgTMaRw7Eb"},{"type":"text","value":" and ","position":{"start":{"line":3,"column":1},"end":{"line":3,"column":1}},"key":"awD4vNR0G2"},{"type":"strong","position":{"start":{"line":3,"column":1},"end":{"line":3,"column":1}},"children":[{"type":"text","value":"information","position":{"start":{"line":3,"column":1},"end":{"line":3,"column":1}},"key":"DmOA1orbji"}],"key":"lsitw6oh8Z"},{"type":"text","value":" are not exactly the same.","position":{"start":{"line":3,"column":1},"end":{"line":3,"column":1}},"key":"Ao13PPtEgm"}],"key":"XsO8pGYLw0"},{"type":"paragraph","position":{"start":{"line":5,"column":1},"end":{"line":5,"column":1}},"children":[{"type":"strong","position":{"start":{"line":5,"column":1},"end":{"line":5,"column":1}},"children":[{"type":"text","value":"Data","position":{"start":{"line":5,"column":1},"end":{"line":5,"column":1}},"key":"AE35T1djnE"}],"key":"SnDTbAuXXI"},{"type":"text","value":" are raw facts or values.","position":{"start":{"line":5,"column":1},"end":{"line":5,"column":1}},"key":"j5aG378wxP"}],"key":"wvN6nNDC3b"},{"type":"paragraph","position":{"start":{"line":7,"column":1},"end":{"line":7,"column":1}},"children":[{"type":"text","value":"Examples:","position":{"start":{"line":7,"column":1},"end":{"line":7,"column":1}},"key":"Gm8mJXF4Or"}],"key":"Lgow5RkMik"},{"type":"table","position":{"start":{"line":9,"column":1},"end":{"line":13,"column":1}},"children":[{"type":"tableRow","position":{"start":{"line":9,"column":1},"end":{"line":9,"column":1}},"children":[{"type":"tableCell","header":true,"position":{"start":{"line":9,"column":1},"end":{"line":9,"column":1}},"children":[{"type":"text","value":"StudentID","position":{"start":{"line":9,"column":1},"end":{"line":9,"column":1}},"key":"g8dMbA8PTB"}],"key":"jDSzrReFZf"},{"type":"tableCell","header":true,"position":{"start":{"line":9,"column":1},"end":{"line":9,"column":1}},"children":[{"type":"text","value":"FirstName","position":{"start":{"line":9,"column":1},"end":{"line":9,"column":1}},"key":"kFYdYxPeKu"}],"key":"tOWtzQu43I"},{"type":"tableCell","header":true,"position":{"start":{"line":9,"column":1},"end":{"line":9,"column":1}},"children":[{"type":"text","value":"LastName","position":{"start":{"line":9,"column":1},"end":{"line":9,"column":1}},"key":"oWl21i76Yd"}],"key":"hVE87oxA7p"},{"type":"tableCell","header":true,"position":{"start":{"line":9,"column":1},"end":{"line":9,"column":1}},"children":[{"type":"text","value":"Major","position":{"start":{"line":9,"column":1},"end":{"line":9,"column":1}},"key":"bolVF1cur2"}],"key":"CXNmQ24lH0"}],"key":"l7AVFLPNrj"},{"type":"tableRow","position":{"start":{"line":11,"column":1},"end":{"line":11,"column":1}},"children":[{"type":"tableCell","position":{"start":{"line":11,"column":1},"end":{"line":11,"column":1}},"children":[{"type":"text","value":"1001","position":{"start":{"line":11,"column":1},"end":{"line":11,"column":1}},"key":"pPAovCougf"}],"key":"PNz4ZtMMKv"},{"type":"tableCell","position":{"start":{"line":11,"column":1},"end":{"line":11,"column":1}},"children":[{"type":"text","value":"Maya","position":{"start":{"line":11,"column":1},"end":{"line":11,"column":1}},"key":"uOsBy8CeeS"}],"key":"MXXG9sIc8e"},{"type":"tableCell","position":{"start":{"line":11,"column":1},"end":{"line":11,"column":1}},"children":[{"type":"text","value":"Johnson","position":{"start":{"line":11,"column":1},"end":{"line":11,"column":1}},"key":"tOasSbarY8"}],"key":"wo6NJyF9TE"},{"type":"tableCell","position":{"start":{"line":11,"column":1},"end":{"line":11,"column":1}},"children":[{"type":"text","value":"IST","position":{"start":{"line":11,"column":1},"end":{"line":11,"column":1}},"key":"V1nlVlR3xx"}],"key":"EQ54FY1sWu"}],"key":"PZJ88Nnveh"},{"type":"tableRow","position":{"start":{"line":12,"column":1},"end":{"line":12,"column":1}},"children":[{"type":"tableCell","position":{"start":{"line":12,"column":1},"end":{"line":12,"column":1}},"children":[{"type":"text","value":"1002","position":{"start":{"line":12,"column":1},"end":{"line":12,"column":1}},"key":"G3Fq39ZEDu"}],"key":"nbaazpqio8"},{"type":"tableCell","position":{"start":{"line":12,"column":1},"end":{"line":12,"column":1}},"children":[{"type":"text","value":"Carlos","position":{"start":{"line":12,"column":1},"end":{"line":12,"column":1}},"key":"nAxRgxL2Zn"}],"key":"SkAdSw3uov"},{"type":"tableCell","position":{"start":{"line":12,"column":1},"end":{"line":12,"column":1}},"children":[{"type":"text","value":"Rivera","position":{"start":{"line":12,"column":1},"end":{"line":12,"column":1}},"key":"xFqWKZzXZB"}],"key":"O1MSVTkBdh"},{"type":"tableCell","position":{"start":{"line":12,"column":1},"end":{"line":12,"column":1}},"children":[{"type":"text","value":"Business","position":{"start":{"line":12,"column":1},"end":{"line":12,"column":1}},"key":"IGPDRsoGPb"}],"key":"GJomCwqT51"}],"key":"jXINT7TC8I"},{"type":"tableRow","position":{"start":{"line":13,"column":1},"end":{"line":13,"column":1}},"children":[{"type":"tableCell","position":{"start":{"line":13,"column":1},"end":{"line":13,"column":1}},"children":[{"type":"text","value":"1003","position":{"start":{"line":13,"column":1},"end":{"line":13,"column":1}},"key":"DyE8FZ80l7"}],"key":"XGkwEKawhK"},{"type":"tableCell","position":{"start":{"line":13,"column":1},"end":{"line":13,"column":1}},"children":[{"type":"text","value":"Amina","position":{"start":{"line":13,"column":1},"end":{"line":13,"column":1}},"key":"Lg8XeB9HUv"}],"key":"xAc7GNjUQ7"},{"type":"tableCell","position":{"start":{"line":13,"column":1},"end":{"line":13,"column":1}},"children":[{"type":"text","value":"Patel","position":{"start":{"line":13,"column":1},"end":{"line":13,"column":1}},"key":"MsV7ESwUHo"}],"key":"by2iSKe5a4"},{"type":"tableCell","position":{"start":{"line":13,"column":1},"end":{"line":13,"column":1}},"children":[{"type":"text","value":"Engineering","position":{"start":{"line":13,"column":1},"end":{"line":13,"column":1}},"key":"AxOgct5N7Y"}],"key":"UWa2kyMdhR"}],"key":"qqjmA5gmGK"}],"key":"REyb2fQuVQ"},{"type":"paragraph","position":{"start":{"line":15,"column":1},"end":{"line":15,"column":1}},"children":[{"type":"strong","position":{"start":{"line":15,"column":1},"end":{"line":15,"column":1}},"children":[{"type":"text","value":"Information","position":{"start":{"line":15,"column":1},"end":{"line":15,"column":1}},"key":"s8upuHpm49"}],"key":"wpedKgwGHr"},{"type":"text","value":" is data that has been organized or interpreted so that it is useful.","position":{"start":{"line":15,"column":1},"end":{"line":15,"column":1}},"key":"bKcMIoXyZB"}],"key":"cfqz4N3GVf"},{"type":"paragraph","position":{"start":{"line":17,"column":1},"end":{"line":17,"column":1}},"children":[{"type":"text","value":"Examples:","position":{"start":{"line":17,"column":1},"end":{"line":17,"column":1}},"key":"dN5qp14MRw"}],"key":"hQukLOyUfY"},{"type":"list","ordered":false,"spread":false,"position":{"start":{"line":19,"column":1},"end":{"line":22,"column":1}},"children":[{"type":"listItem","spread":true,"position":{"start":{"line":19,"column":1},"end":{"line":19,"column":1}},"children":[{"type":"paragraph","children":[{"type":"text","value":"There are 3 students in the sample.","position":{"start":{"line":19,"column":1},"end":{"line":19,"column":1}},"key":"xlwIDsJKa0"}],"key":"ucjrNSA2ju"}],"key":"uMbciS9Zx5"},{"type":"listItem","spread":true,"position":{"start":{"line":20,"column":1},"end":{"line":20,"column":1}},"children":[{"type":"paragraph","children":[{"type":"text","value":"One student is majoring in Business.","position":{"start":{"line":20,"column":1},"end":{"line":20,"column":1}},"key":"q6SYWK5mFO"}],"key":"wEAy385YmQ"}],"key":"XnJrXVW6Gp"},{"type":"listItem","spread":true,"position":{"start":{"line":21,"column":1},"end":{"line":22,"column":1}},"children":[{"type":"paragraph","children":[{"type":"text","value":"Student 1003 is Amina Patel.","position":{"start":{"line":21,"column":1},"end":{"line":21,"column":1}},"key":"pLSwKTTe5b"}],"key":"hTw3WzJc7i"}],"key":"MFNAmilOJd"}],"key":"x4bCiHOtWA"},{"type":"paragraph","position":{"start":{"line":23,"column":1},"end":{"line":23,"column":1}},"children":[{"type":"text","value":"A database helps turn raw data into useful information.","position":{"start":{"line":23,"column":1},"end":{"line":23,"column":1}},"key":"S8dAkUvUHd"}],"key":"qgddQ0I5MF"}],"key":"yEw3ZiXQpi"},{"type":"block","kind":"notebook-content","children":[{"type":"heading","depth":2,"position":{"start":{"line":1,"column":1},"end":{"line":1,"column":1}},"children":[{"type":"text","value":"1.3 What Is a Database?","position":{"start":{"line":1,"column":1},"end":{"line":1,"column":1}},"key":"hDSErFP0F6"}],"identifier":"id-1-3-what-is-a-database","label":"1.3 What Is a Database?","html_id":"id-1-3-what-is-a-database","implicit":true,"key":"qRijkzlkVm"},{"type":"paragraph","position":{"start":{"line":3,"column":1},"end":{"line":3,"column":1}},"children":[{"type":"text","value":"A ","position":{"start":{"line":3,"column":1},"end":{"line":3,"column":1}},"key":"bmywuaLtYr"},{"type":"strong","position":{"start":{"line":3,"column":1},"end":{"line":3,"column":1}},"children":[{"type":"text","value":"database","position":{"start":{"line":3,"column":1},"end":{"line":3,"column":1}},"key":"GasLJMCHv2"}],"key":"UZKMfQ2bJf"},{"type":"text","value":" is an organized collection of related data.","position":{"start":{"line":3,"column":1},"end":{"line":3,"column":1}},"key":"oz0CuCkQgz"}],"key":"ZAYsscWLf7"},{"type":"paragraph","position":{"start":{"line":5,"column":1},"end":{"line":5,"column":1}},"children":[{"type":"text","value":"The word ","position":{"start":{"line":5,"column":1},"end":{"line":5,"column":1}},"key":"fzE5QBdRvo"},{"type":"strong","position":{"start":{"line":5,"column":1},"end":{"line":5,"column":1}},"children":[{"type":"text","value":"organized","position":{"start":{"line":5,"column":1},"end":{"line":5,"column":1}},"key":"Ys8PKoYD45"}],"key":"p4Kf7TjGmQ"},{"type":"text","value":" is important. A random list of names is not usually enough. A useful database has structure, rules, and relationships.","position":{"start":{"line":5,"column":1},"end":{"line":5,"column":1}},"key":"YWUbrFtsop"}],"key":"eOh0HENM4q"},{"type":"paragraph","position":{"start":{"line":7,"column":1},"end":{"line":7,"column":1}},"children":[{"type":"text","value":"For example, a college registration database might include:","position":{"start":{"line":7,"column":1},"end":{"line":7,"column":1}},"key":"YpmtLat0RG"}],"key":"RjY4tP4sg3"},{"type":"list","ordered":false,"spread":false,"position":{"start":{"line":9,"column":1},"end":{"line":14,"column":1}},"children":[{"type":"listItem","spread":true,"position":{"start":{"line":9,"column":1},"end":{"line":9,"column":1}},"children":[{"type":"paragraph","children":[{"type":"text","value":"Students","position":{"start":{"line":9,"column":1},"end":{"line":9,"column":1}},"key":"wExpNvfMh8"}],"key":"V6wpQiUsz3"}],"key":"gtQCEZZWJX"},{"type":"listItem","spread":true,"position":{"start":{"line":10,"column":1},"end":{"line":10,"column":1}},"children":[{"type":"paragraph","children":[{"type":"text","value":"Courses","position":{"start":{"line":10,"column":1},"end":{"line":10,"column":1}},"key":"O4EaP4M8S3"}],"key":"vbqlATRyb5"}],"key":"NtLr0LaNld"},{"type":"listItem","spread":true,"position":{"start":{"line":11,"column":1},"end":{"line":11,"column":1}},"children":[{"type":"paragraph","children":[{"type":"text","value":"Instructors","position":{"start":{"line":11,"column":1},"end":{"line":11,"column":1}},"key":"p25IGbSDpp"}],"key":"vkWl6653p4"}],"key":"GU0eCN0LNf"},{"type":"listItem","spread":true,"position":{"start":{"line":12,"column":1},"end":{"line":12,"column":1}},"children":[{"type":"paragraph","children":[{"type":"text","value":"Course sections","position":{"start":{"line":12,"column":1},"end":{"line":12,"column":1}},"key":"UWAW3JFZSY"}],"key":"aH30cHfrg6"}],"key":"cEWvxaCkwd"},{"type":"listItem","spread":true,"position":{"start":{"line":13,"column":1},"end":{"line":14,"column":1}},"children":[{"type":"paragraph","children":[{"type":"text","value":"Enrollments","position":{"start":{"line":13,"column":1},"end":{"line":13,"column":1}},"key":"WCP2QGFD6C"}],"key":"h91eFNNEcX"}],"key":"vYpdfHplKs"}],"key":"QRS4bSI4HU"},{"type":"paragraph","position":{"start":{"line":15,"column":1},"end":{"line":15,"column":1}},"children":[{"type":"text","value":"These are related. A student enrolls in a course section. A course section is taught by an instructor. A course belongs to a department.","position":{"start":{"line":15,"column":1},"end":{"line":15,"column":1}},"key":"gxKysmc5LF"}],"key":"NVNs3Yzf0v"},{"type":"paragraph","position":{"start":{"line":17,"column":1},"end":{"line":17,"column":1}},"children":[{"type":"text","value":"A database allows these related pieces of data to be stored together in a structured way.","position":{"start":{"line":17,"column":1},"end":{"line":17,"column":1}},"key":"urgVvX7rIK"}],"key":"jnmUUe8l6s"}],"key":"nSZOwj0OX7"},{"type":"block","kind":"notebook-content","children":[{"type":"heading","depth":2,"position":{"start":{"line":1,"column":1},"end":{"line":1,"column":1}},"children":[{"type":"text","value":"1.4 What Is a DBMS?","position":{"start":{"line":1,"column":1},"end":{"line":1,"column":1}},"key":"SwuoKp591t"}],"identifier":"id-1-4-what-is-a-dbms","label":"1.4 What Is a DBMS?","html_id":"id-1-4-what-is-a-dbms","implicit":true,"key":"MUQrfQBZuQ"},{"type":"paragraph","position":{"start":{"line":3,"column":1},"end":{"line":3,"column":1}},"children":[{"type":"text","value":"A ","position":{"start":{"line":3,"column":1},"end":{"line":3,"column":1}},"key":"VI4d74PadV"},{"type":"strong","position":{"start":{"line":3,"column":1},"end":{"line":3,"column":1}},"children":[{"type":"text","value":"Database Management System","position":{"start":{"line":3,"column":1},"end":{"line":3,"column":1}},"key":"tg5tlGMifT"}],"key":"COUvOQjJLc"},{"type":"text","value":", or ","position":{"start":{"line":3,"column":1},"end":{"line":3,"column":1}},"key":"quns5slkLU"},{"type":"strong","position":{"start":{"line":3,"column":1},"end":{"line":3,"column":1}},"children":[{"type":"text","value":"DBMS","position":{"start":{"line":3,"column":1},"end":{"line":3,"column":1}},"key":"GTDBMtOguG"}],"key":"kkwrZs6Uwf"},{"type":"text","value":", is software used to create, manage, and interact with databases.","position":{"start":{"line":3,"column":1},"end":{"line":3,"column":1}},"key":"szNd9lzpVI"}],"key":"Ra5WNw8ZfH"},{"type":"paragraph","position":{"start":{"line":5,"column":1},"end":{"line":5,"column":1}},"children":[{"type":"text","value":"Examples of database management systems include:","position":{"start":{"line":5,"column":1},"end":{"line":5,"column":1}},"key":"IInRaZpVOO"}],"key":"vjVu99nRL0"},{"type":"list","ordered":false,"spread":false,"position":{"start":{"line":7,"column":1},"end":{"line":12,"column":1}},"children":[{"type":"listItem","spread":true,"position":{"start":{"line":7,"column":1},"end":{"line":7,"column":1}},"children":[{"type":"paragraph","children":[{"type":"text","value":"SQLite","position":{"start":{"line":7,"column":1},"end":{"line":7,"column":1}},"key":"as70iPVpHW"}],"key":"aIuGOP7aGB"}],"key":"hDsK9mqzaO"},{"type":"listItem","spread":true,"position":{"start":{"line":8,"column":1},"end":{"line":8,"column":1}},"children":[{"type":"paragraph","children":[{"type":"text","value":"MySQL","position":{"start":{"line":8,"column":1},"end":{"line":8,"column":1}},"key":"p3HOHvD2d1"}],"key":"Tl333489kU"}],"key":"UnETqgzwnZ"},{"type":"listItem","spread":true,"position":{"start":{"line":9,"column":1},"end":{"line":9,"column":1}},"children":[{"type":"paragraph","children":[{"type":"text","value":"PostgreSQL","position":{"start":{"line":9,"column":1},"end":{"line":9,"column":1}},"key":"EI5nuY3AjP"}],"key":"iCCQu4ALpN"}],"key":"VGxOsJZiDt"},{"type":"listItem","spread":true,"position":{"start":{"line":10,"column":1},"end":{"line":10,"column":1}},"children":[{"type":"paragraph","children":[{"type":"text","value":"Microsoft SQL Server","position":{"start":{"line":10,"column":1},"end":{"line":10,"column":1}},"key":"IhNYL2e1nb"}],"key":"bCzq3J9ner"}],"key":"eIYrAnBeg6"},{"type":"listItem","spread":true,"position":{"start":{"line":11,"column":1},"end":{"line":12,"column":1}},"children":[{"type":"paragraph","children":[{"type":"text","value":"Oracle Database","position":{"start":{"line":11,"column":1},"end":{"line":11,"column":1}},"key":"BJoH2twW9E"}],"key":"GjBQ7TVoCT"}],"key":"b6BGgewhkW"}],"key":"OMxIVC35s2"},{"type":"paragraph","position":{"start":{"line":13,"column":1},"end":{"line":14,"column":1}},"children":[{"type":"text","value":"The database is the stored data.","position":{"start":{"line":13,"column":1},"end":{"line":13,"column":1}},"key":"FeOxGnTXQ0"},{"type":"break","position":{"start":{"line":13,"column":1},"end":{"line":13,"column":1}},"key":"aClic6lqYG"},{"type":"text","value":"The DBMS is the software that manages the database.","position":{"start":{"line":13,"column":1},"end":{"line":13,"column":1}},"key":"FTruPW1NeT"}],"key":"Crm2Q9KHzf"},{"type":"paragraph","position":{"start":{"line":16,"column":1},"end":{"line":16,"column":1}},"children":[{"type":"text","value":"A DBMS helps users:","position":{"start":{"line":16,"column":1},"end":{"line":16,"column":1}},"key":"yq9jH9rv9v"}],"key":"CD8YdvQwmb"},{"type":"list","ordered":false,"spread":false,"position":{"start":{"line":18,"column":1},"end":{"line":24,"column":1}},"children":[{"type":"listItem","spread":true,"position":{"start":{"line":18,"column":1},"end":{"line":18,"column":1}},"children":[{"type":"paragraph","children":[{"type":"text","value":"Add new data","position":{"start":{"line":18,"column":1},"end":{"line":18,"column":1}},"key":"U76PNeKWXp"}],"key":"MNlXBWiDoG"}],"key":"dx1nnAkftO"},{"type":"listItem","spread":true,"position":{"start":{"line":19,"column":1},"end":{"line":19,"column":1}},"children":[{"type":"paragraph","children":[{"type":"text","value":"Update existing data","position":{"start":{"line":19,"column":1},"end":{"line":19,"column":1}},"key":"PVazysrFsM"}],"key":"ezb2voFxAu"}],"key":"FesrR2UKVH"},{"type":"listItem","spread":true,"position":{"start":{"line":20,"column":1},"end":{"line":20,"column":1}},"children":[{"type":"paragraph","children":[{"type":"text","value":"Delete data","position":{"start":{"line":20,"column":1},"end":{"line":20,"column":1}},"key":"Iis9ZfKRyO"}],"key":"NikfY6BHQd"}],"key":"N1NMuVCKon"},{"type":"listItem","spread":true,"position":{"start":{"line":21,"column":1},"end":{"line":21,"column":1}},"children":[{"type":"paragraph","children":[{"type":"text","value":"Search data","position":{"start":{"line":21,"column":1},"end":{"line":21,"column":1}},"key":"rrq1Em1hPH"}],"key":"RVNpgGZoRW"}],"key":"Z8zGYPv8BY"},{"type":"listItem","spread":true,"position":{"start":{"line":22,"column":1},"end":{"line":22,"column":1}},"children":[{"type":"paragraph","children":[{"type":"text","value":"Protect data","position":{"start":{"line":22,"column":1},"end":{"line":22,"column":1}},"key":"jSGBoQgqsM"}],"key":"b0dRZYD3NY"}],"key":"NwzlqYa6bc"},{"type":"listItem","spread":true,"position":{"start":{"line":23,"column":1},"end":{"line":23,"column":1}},"children":[{"type":"paragraph","children":[{"type":"text","value":"Control who can access data","position":{"start":{"line":23,"column":1},"end":{"line":23,"column":1}},"key":"IDnnstkqqK"}],"key":"NiXOfGn7VN"}],"key":"YqFJQUtmqG"},{"type":"listItem","spread":true,"position":{"start":{"line":24,"column":1},"end":{"line":24,"column":1}},"children":[{"type":"paragraph","children":[{"type":"text","value":"Prevent inconsistent or invalid data","position":{"start":{"line":24,"column":1},"end":{"line":24,"column":1}},"key":"Xd3vO3coNv"}],"key":"cOBhk7C1Jt"}],"key":"tHFE5YFBRD"}],"key":"fNNyHHmXCi"}],"key":"AWI7DbYssA"},{"type":"block","kind":"notebook-content","children":[{"type":"heading","depth":2,"position":{"start":{"line":1,"column":1},"end":{"line":1,"column":1}},"children":[{"type":"text","value":"1.5 Databases vs. Spreadsheets","position":{"start":{"line":1,"column":1},"end":{"line":1,"column":1}},"key":"NnpauvcnzG"}],"identifier":"id-1-5-databases-vs-spreadsheets","label":"1.5 Databases vs. Spreadsheets","html_id":"id-1-5-databases-vs-spreadsheets","implicit":true,"key":"XOPn2wHJiF"},{"type":"paragraph","position":{"start":{"line":3,"column":1},"end":{"line":3,"column":1}},"children":[{"type":"text","value":"Spreadsheets are useful tools, especially for small tasks. However, as data becomes larger, more connected, or shared by many users, spreadsheets can become difficult to manage.","position":{"start":{"line":3,"column":1},"end":{"line":3,"column":1}},"key":"A0a19ySh65"}],"key":"XEu3ebTfdZ"},{"type":"table","position":{"start":{"line":5,"column":1},"end":{"line":11,"column":1}},"children":[{"type":"tableRow","position":{"start":{"line":5,"column":1},"end":{"line":5,"column":1}},"children":[{"type":"tableCell","header":true,"position":{"start":{"line":5,"column":1},"end":{"line":5,"column":1}},"children":[{"type":"text","value":"Spreadsheet","position":{"start":{"line":5,"column":1},"end":{"line":5,"column":1}},"key":"CqFsXsa3GE"}],"key":"vqF0Djzlxv"},{"type":"tableCell","header":true,"position":{"start":{"line":5,"column":1},"end":{"line":5,"column":1}},"children":[{"type":"text","value":"Database","position":{"start":{"line":5,"column":1},"end":{"line":5,"column":1}},"key":"QYbfnDuZio"}],"key":"F4oS5uirhs"}],"key":"tAXweG66mX"},{"type":"tableRow","position":{"start":{"line":7,"column":1},"end":{"line":7,"column":1}},"children":[{"type":"tableCell","position":{"start":{"line":7,"column":1},"end":{"line":7,"column":1}},"children":[{"type":"text","value":"Good for small, simple datasets","position":{"start":{"line":7,"column":1},"end":{"line":7,"column":1}},"key":"UAzNV8NZHO"}],"key":"e2LBEPYHnP"},{"type":"tableCell","position":{"start":{"line":7,"column":1},"end":{"line":7,"column":1}},"children":[{"type":"text","value":"Good for larger, structured datasets","position":{"start":{"line":7,"column":1},"end":{"line":7,"column":1}},"key":"Lxtg13ZkDT"}],"key":"hv4ZUx519D"}],"key":"yvY0VfSSyf"},{"type":"tableRow","position":{"start":{"line":8,"column":1},"end":{"line":8,"column":1}},"children":[{"type":"tableCell","position":{"start":{"line":8,"column":1},"end":{"line":8,"column":1}},"children":[{"type":"text","value":"Often edited manually","position":{"start":{"line":8,"column":1},"end":{"line":8,"column":1}},"key":"a5Eer57ued"}],"key":"XylYsyLYbi"},{"type":"tableCell","position":{"start":{"line":8,"column":1},"end":{"line":8,"column":1}},"children":[{"type":"text","value":"Often managed using rules and queries","position":{"start":{"line":8,"column":1},"end":{"line":8,"column":1}},"key":"BvWWzFwJjp"}],"key":"nWbibIhwbz"}],"key":"bmXP8DJ0rf"},{"type":"tableRow","position":{"start":{"line":9,"column":1},"end":{"line":9,"column":1}},"children":[{"type":"tableCell","position":{"start":{"line":9,"column":1},"end":{"line":9,"column":1}},"children":[{"type":"text","value":"Easy to duplicate inconsistent data","position":{"start":{"line":9,"column":1},"end":{"line":9,"column":1}},"key":"dfa8dGWfdS"}],"key":"ipPQ4gLMwn"},{"type":"tableCell","position":{"start":{"line":9,"column":1},"end":{"line":9,"column":1}},"children":[{"type":"text","value":"Designed to reduce unnecessary duplication","position":{"start":{"line":9,"column":1},"end":{"line":9,"column":1}},"key":"J4JWUT5uRP"}],"key":"xMSaxg3F7v"}],"key":"ztfumEOaR4"},{"type":"tableRow","position":{"start":{"line":10,"column":1},"end":{"line":10,"column":1}},"children":[{"type":"tableCell","position":{"start":{"line":10,"column":1},"end":{"line":10,"column":1}},"children":[{"type":"text","value":"Limited control over relationships","position":{"start":{"line":10,"column":1},"end":{"line":10,"column":1}},"key":"Js8b96wVVd"}],"key":"M4YRw46zXL"},{"type":"tableCell","position":{"start":{"line":10,"column":1},"end":{"line":10,"column":1}},"children":[{"type":"text","value":"Designed to model relationships","position":{"start":{"line":10,"column":1},"end":{"line":10,"column":1}},"key":"lEdCYQt1Q3"}],"key":"m8RIHeznJQ"}],"key":"ga0KFTMSo3"},{"type":"tableRow","position":{"start":{"line":11,"column":1},"end":{"line":11,"column":1}},"children":[{"type":"tableCell","position":{"start":{"line":11,"column":1},"end":{"line":11,"column":1}},"children":[{"type":"text","value":"Not ideal for many users editing at once","position":{"start":{"line":11,"column":1},"end":{"line":11,"column":1}},"key":"f3wWkdAgP4"}],"key":"TRJTnwiX1T"},{"type":"tableCell","position":{"start":{"line":11,"column":1},"end":{"line":11,"column":1}},"children":[{"type":"text","value":"Better for shared organizational systems","position":{"start":{"line":11,"column":1},"end":{"line":11,"column":1}},"key":"ipi1jKztnp"}],"key":"hbzQKRCseS"}],"key":"TzJDYnHlwg"}],"key":"rBGsMWFyl1"},{"type":"paragraph","position":{"start":{"line":13,"column":1},"end":{"line":13,"column":1}},"children":[{"type":"text","value":"For example, a spreadsheet might store customer and order data in one large table. A database would usually separate customers, orders, and products into different but related tables.","position":{"start":{"line":13,"column":1},"end":{"line":13,"column":1}},"key":"QxWxn9UWUb"}],"key":"eeFB6GDqQ8"}],"key":"eIqukcO7wR"},{"type":"block","kind":"notebook-content","children":[{"type":"heading","depth":2,"position":{"start":{"line":1,"column":1},"end":{"line":1,"column":1}},"children":[{"type":"text","value":"1.6 Tables, Rows, and Columns","position":{"start":{"line":1,"column":1},"end":{"line":1,"column":1}},"key":"NlrWNTtlvR"}],"identifier":"id-1-6-tables-rows-and-columns","label":"1.6 Tables, Rows, and Columns","html_id":"id-1-6-tables-rows-and-columns","implicit":true,"key":"bu5iBK10gj"},{"type":"paragraph","position":{"start":{"line":3,"column":1},"end":{"line":3,"column":1}},"children":[{"type":"text","value":"Relational databases organize data into ","position":{"start":{"line":3,"column":1},"end":{"line":3,"column":1}},"key":"bcEOAMfSYL"},{"type":"strong","position":{"start":{"line":3,"column":1},"end":{"line":3,"column":1}},"children":[{"type":"text","value":"tables","position":{"start":{"line":3,"column":1},"end":{"line":3,"column":1}},"key":"I3E2H0Jyg1"}],"key":"d7CpKNHyf2"},{"type":"text","value":".","position":{"start":{"line":3,"column":1},"end":{"line":3,"column":1}},"key":"BhQCfUanz2"}],"key":"dCHgoElTq0"},{"type":"paragraph","position":{"start":{"line":5,"column":1},"end":{"line":5,"column":1}},"children":[{"type":"text","value":"A table is made of:","position":{"start":{"line":5,"column":1},"end":{"line":5,"column":1}},"key":"TTT3E74TCf"}],"key":"zdlqlmuDuc"},{"type":"list","ordered":false,"spread":false,"position":{"start":{"line":7,"column":1},"end":{"line":10,"column":1}},"children":[{"type":"listItem","spread":true,"position":{"start":{"line":7,"column":1},"end":{"line":7,"column":1}},"children":[{"type":"paragraph","children":[{"type":"strong","position":{"start":{"line":7,"column":1},"end":{"line":7,"column":1}},"children":[{"type":"text","value":"Columns","position":{"start":{"line":7,"column":1},"end":{"line":7,"column":1}},"key":"PdN4FBgncU"}],"key":"enFPk4uoYH"},{"type":"text","value":": categories or fields of data","position":{"start":{"line":7,"column":1},"end":{"line":7,"column":1}},"key":"gtf6H5WQ49"}],"key":"ZP6DkUAzbA"}],"key":"t1bcUDc0Q6"},{"type":"listItem","spread":true,"position":{"start":{"line":8,"column":1},"end":{"line":8,"column":1}},"children":[{"type":"paragraph","children":[{"type":"strong","position":{"start":{"line":8,"column":1},"end":{"line":8,"column":1}},"children":[{"type":"text","value":"Rows","position":{"start":{"line":8,"column":1},"end":{"line":8,"column":1}},"key":"XpvRavzr6L"}],"key":"imXHH616iy"},{"type":"text","value":": individual records","position":{"start":{"line":8,"column":1},"end":{"line":8,"column":1}},"key":"d6SXrmfjHb"}],"key":"W07cl0SuFc"}],"key":"eUUXStcS2X"},{"type":"listItem","spread":true,"position":{"start":{"line":9,"column":1},"end":{"line":10,"column":1}},"children":[{"type":"paragraph","children":[{"type":"strong","position":{"start":{"line":9,"column":1},"end":{"line":9,"column":1}},"children":[{"type":"text","value":"Cells","position":{"start":{"line":9,"column":1},"end":{"line":9,"column":1}},"key":"rQVSA9SzAF"}],"key":"fU8aGCtuSH"},{"type":"text","value":": individual values","position":{"start":{"line":9,"column":1},"end":{"line":9,"column":1}},"key":"FTJnCL2var"}],"key":"BvRckIrxPj"}],"key":"rqH22sfqQT"}],"key":"sjqu3qhYYh"},{"type":"paragraph","position":{"start":{"line":11,"column":1},"end":{"line":11,"column":1}},"children":[{"type":"text","value":"Example table: ","position":{"start":{"line":11,"column":1},"end":{"line":11,"column":1}},"key":"G15ILuiGyJ"},{"type":"inlineCode","value":"Student","position":{"start":{"line":11,"column":1},"end":{"line":11,"column":1}},"key":"JPjlWAwzF5"}],"key":"dVS4f0waD8"},{"type":"table","position":{"start":{"line":13,"column":1},"end":{"line":17,"column":1}},"children":[{"type":"tableRow","position":{"start":{"line":13,"column":1},"end":{"line":13,"column":1}},"children":[{"type":"tableCell","header":true,"position":{"start":{"line":13,"column":1},"end":{"line":13,"column":1}},"children":[{"type":"text","value":"StudentID","position":{"start":{"line":13,"column":1},"end":{"line":13,"column":1}},"key":"cxKsqSq5Um"}],"key":"aWU7eNaSDK"},{"type":"tableCell","header":true,"position":{"start":{"line":13,"column":1},"end":{"line":13,"column":1}},"children":[{"type":"text","value":"FirstName","position":{"start":{"line":13,"column":1},"end":{"line":13,"column":1}},"key":"YfRRcKwwAe"}],"key":"mDfdQsRkOt"},{"type":"tableCell","header":true,"position":{"start":{"line":13,"column":1},"end":{"line":13,"column":1}},"children":[{"type":"text","value":"LastName","position":{"start":{"line":13,"column":1},"end":{"line":13,"column":1}},"key":"jQz8uMGPcE"}],"key":"c77qlh6NH1"},{"type":"tableCell","header":true,"position":{"start":{"line":13,"column":1},"end":{"line":13,"column":1}},"children":[{"type":"text","value":"Major","position":{"start":{"line":13,"column":1},"end":{"line":13,"column":1}},"key":"YTt2jtJztu"}],"key":"xjKrxF3Whv"}],"key":"wSsWHEpoOi"},{"type":"tableRow","position":{"start":{"line":15,"column":1},"end":{"line":15,"column":1}},"children":[{"type":"tableCell","position":{"start":{"line":15,"column":1},"end":{"line":15,"column":1}},"children":[{"type":"text","value":"1001","position":{"start":{"line":15,"column":1},"end":{"line":15,"column":1}},"key":"RE9wrHkOGc"}],"key":"Fg862RcsA2"},{"type":"tableCell","position":{"start":{"line":15,"column":1},"end":{"line":15,"column":1}},"children":[{"type":"text","value":"Maya","position":{"start":{"line":15,"column":1},"end":{"line":15,"column":1}},"key":"pH3HmEwzY5"}],"key":"num3M4gUyU"},{"type":"tableCell","position":{"start":{"line":15,"column":1},"end":{"line":15,"column":1}},"children":[{"type":"text","value":"Johnson","position":{"start":{"line":15,"column":1},"end":{"line":15,"column":1}},"key":"AiMSgMPoaW"}],"key":"LUBceqhGn1"},{"type":"tableCell","position":{"start":{"line":15,"column":1},"end":{"line":15,"column":1}},"children":[{"type":"text","value":"IST","position":{"start":{"line":15,"column":1},"end":{"line":15,"column":1}},"key":"BYKzuI748E"}],"key":"sDjBn5Yq5S"}],"key":"rsNeRxPZVX"},{"type":"tableRow","position":{"start":{"line":16,"column":1},"end":{"line":16,"column":1}},"children":[{"type":"tableCell","position":{"start":{"line":16,"column":1},"end":{"line":16,"column":1}},"children":[{"type":"text","value":"1002","position":{"start":{"line":16,"column":1},"end":{"line":16,"column":1}},"key":"CIq18eKzno"}],"key":"Ky1HGlz36l"},{"type":"tableCell","position":{"start":{"line":16,"column":1},"end":{"line":16,"column":1}},"children":[{"type":"text","value":"Carlos","position":{"start":{"line":16,"column":1},"end":{"line":16,"column":1}},"key":"yMu3gUS1C6"}],"key":"qUMLcsjqz5"},{"type":"tableCell","position":{"start":{"line":16,"column":1},"end":{"line":16,"column":1}},"children":[{"type":"text","value":"Rivera","position":{"start":{"line":16,"column":1},"end":{"line":16,"column":1}},"key":"L6NDRmXyYE"}],"key":"GRauHBDMoN"},{"type":"tableCell","position":{"start":{"line":16,"column":1},"end":{"line":16,"column":1}},"children":[{"type":"text","value":"Business","position":{"start":{"line":16,"column":1},"end":{"line":16,"column":1}},"key":"yAghBSOIS7"}],"key":"auQ59yR9xU"}],"key":"DEHhLGYI94"},{"type":"tableRow","position":{"start":{"line":17,"column":1},"end":{"line":17,"column":1}},"children":[{"type":"tableCell","position":{"start":{"line":17,"column":1},"end":{"line":17,"column":1}},"children":[{"type":"text","value":"1003","position":{"start":{"line":17,"column":1},"end":{"line":17,"column":1}},"key":"TLLFAIWbD6"}],"key":"IELtIAW6vL"},{"type":"tableCell","position":{"start":{"line":17,"column":1},"end":{"line":17,"column":1}},"children":[{"type":"text","value":"Amina","position":{"start":{"line":17,"column":1},"end":{"line":17,"column":1}},"key":"XFM7wSLsMq"}],"key":"YEOx23G06y"},{"type":"tableCell","position":{"start":{"line":17,"column":1},"end":{"line":17,"column":1}},"children":[{"type":"text","value":"Patel","position":{"start":{"line":17,"column":1},"end":{"line":17,"column":1}},"key":"aD0TYj5z9E"}],"key":"UOxUDMKp2J"},{"type":"tableCell","position":{"start":{"line":17,"column":1},"end":{"line":17,"column":1}},"children":[{"type":"text","value":"Engineering","position":{"start":{"line":17,"column":1},"end":{"line":17,"column":1}},"key":"gn219eHTMZ"}],"key":"GdpD1wUrHf"}],"key":"Ofqt1WeGSV"}],"key":"QPN1aG367v"},{"type":"paragraph","position":{"start":{"line":19,"column":1},"end":{"line":19,"column":1}},"children":[{"type":"text","value":"In database terminology:","position":{"start":{"line":19,"column":1},"end":{"line":19,"column":1}},"key":"sngpo7nFcb"}],"key":"nvTJ3Dl8U0"},{"type":"list","ordered":false,"spread":false,"position":{"start":{"line":21,"column":1},"end":{"line":24,"column":1}},"children":[{"type":"listItem","spread":true,"position":{"start":{"line":21,"column":1},"end":{"line":21,"column":1}},"children":[{"type":"paragraph","children":[{"type":"text","value":"A table is often called a ","position":{"start":{"line":21,"column":1},"end":{"line":21,"column":1}},"key":"yeiMH78xLR"},{"type":"strong","position":{"start":{"line":21,"column":1},"end":{"line":21,"column":1}},"children":[{"type":"text","value":"relation","position":{"start":{"line":21,"column":1},"end":{"line":21,"column":1}},"key":"RVTOYXBggJ"}],"key":"GLqBEg74v8"},{"type":"text","value":".","position":{"start":{"line":21,"column":1},"end":{"line":21,"column":1}},"key":"WyxTRRXSlp"}],"key":"nrKM5SP5NG"}],"key":"X2cvDSH3Hd"},{"type":"listItem","spread":true,"position":{"start":{"line":22,"column":1},"end":{"line":22,"column":1}},"children":[{"type":"paragraph","children":[{"type":"text","value":"A row is often called a ","position":{"start":{"line":22,"column":1},"end":{"line":22,"column":1}},"key":"SLPxPBMOhT"},{"type":"strong","position":{"start":{"line":22,"column":1},"end":{"line":22,"column":1}},"children":[{"type":"text","value":"tuple","position":{"start":{"line":22,"column":1},"end":{"line":22,"column":1}},"key":"u6JBEAMoNy"}],"key":"aAC0vmlsqo"},{"type":"text","value":".","position":{"start":{"line":22,"column":1},"end":{"line":22,"column":1}},"key":"HPd4LhV5dY"}],"key":"R5L1sDM3Kr"}],"key":"kThUaaIcUl"},{"type":"listItem","spread":true,"position":{"start":{"line":23,"column":1},"end":{"line":24,"column":1}},"children":[{"type":"paragraph","children":[{"type":"text","value":"A column is often called an ","position":{"start":{"line":23,"column":1},"end":{"line":23,"column":1}},"key":"RyBoZxIEDq"},{"type":"strong","position":{"start":{"line":23,"column":1},"end":{"line":23,"column":1}},"children":[{"type":"text","value":"attribute","position":{"start":{"line":23,"column":1},"end":{"line":23,"column":1}},"key":"pAtUzdICXc"}],"key":"IHyMKeGrHR"},{"type":"text","value":".","position":{"start":{"line":23,"column":1},"end":{"line":23,"column":1}},"key":"haMQLuUcVa"}],"key":"uJelachqbu"}],"key":"rPdyySq4pU"}],"key":"H4rp0n8gX1"},{"type":"paragraph","position":{"start":{"line":25,"column":1},"end":{"line":25,"column":1}},"children":[{"type":"text","value":"We will use both everyday language and formal database language throughout this book.","position":{"start":{"line":25,"column":1},"end":{"line":25,"column":1}},"key":"LwrzM4eWZs"}],"key":"WkNVMdk83Q"}],"key":"gQ7w2Z1wRZ"},{"type":"block","kind":"notebook-content","children":[{"type":"heading","depth":2,"position":{"start":{"line":1,"column":1},"end":{"line":1,"column":1}},"children":[{"type":"text","value":"1.7 A First Look at SQL","position":{"start":{"line":1,"column":1},"end":{"line":1,"column":1}},"key":"sv1xaOnVKP"}],"identifier":"id-1-7-a-first-look-at-sql","label":"1.7 A First Look at SQL","html_id":"id-1-7-a-first-look-at-sql","implicit":true,"key":"RZxcMwiFpv"},{"type":"paragraph","position":{"start":{"line":3,"column":1},"end":{"line":3,"column":1}},"children":[{"type":"strong","position":{"start":{"line":3,"column":1},"end":{"line":3,"column":1}},"children":[{"type":"text","value":"SQL","position":{"start":{"line":3,"column":1},"end":{"line":3,"column":1}},"key":"uEFDucsTEd"}],"key":"jm2cStFgkQ"},{"type":"text","value":" stands for ","position":{"start":{"line":3,"column":1},"end":{"line":3,"column":1}},"key":"COXHk1OGm9"},{"type":"strong","position":{"start":{"line":3,"column":1},"end":{"line":3,"column":1}},"children":[{"type":"text","value":"Structured Query Language","position":{"start":{"line":3,"column":1},"end":{"line":3,"column":1}},"key":"MCol30wxet"}],"key":"MyOMCnMxE0"},{"type":"text","value":".","position":{"start":{"line":3,"column":1},"end":{"line":3,"column":1}},"key":"oYydzrizY0"}],"key":"z05tHBTHeI"},{"type":"paragraph","position":{"start":{"line":5,"column":1},"end":{"line":5,"column":1}},"children":[{"type":"text","value":"SQL is used to communicate with relational databases. SQL can be used to:","position":{"start":{"line":5,"column":1},"end":{"line":5,"column":1}},"key":"TLQBmVtuI1"}],"key":"p8Swv7lTXl"},{"type":"list","ordered":false,"spread":false,"position":{"start":{"line":7,"column":1},"end":{"line":13,"column":1}},"children":[{"type":"listItem","spread":true,"position":{"start":{"line":7,"column":1},"end":{"line":7,"column":1}},"children":[{"type":"paragraph","children":[{"type":"text","value":"Create tables","position":{"start":{"line":7,"column":1},"end":{"line":7,"column":1}},"key":"x7idUwXJxF"}],"key":"SJhiT0oxMp"}],"key":"iuzYkswRGx"},{"type":"listItem","spread":true,"position":{"start":{"line":8,"column":1},"end":{"line":8,"column":1}},"children":[{"type":"paragraph","children":[{"type":"text","value":"Insert data","position":{"start":{"line":8,"column":1},"end":{"line":8,"column":1}},"key":"Ke4oQ8d5jJ"}],"key":"uwl9Juw2lg"}],"key":"x4FzNfCsys"},{"type":"listItem","spread":true,"position":{"start":{"line":9,"column":1},"end":{"line":9,"column":1}},"children":[{"type":"paragraph","children":[{"type":"text","value":"Retrieve data","position":{"start":{"line":9,"column":1},"end":{"line":9,"column":1}},"key":"lQQlEsGzzQ"}],"key":"g77IztKg9m"}],"key":"D1aKltv001"},{"type":"listItem","spread":true,"position":{"start":{"line":10,"column":1},"end":{"line":10,"column":1}},"children":[{"type":"paragraph","children":[{"type":"text","value":"Update data","position":{"start":{"line":10,"column":1},"end":{"line":10,"column":1}},"key":"LNCzNGrYtr"}],"key":"HisYSXAUtw"}],"key":"OjZhp8Rqym"},{"type":"listItem","spread":true,"position":{"start":{"line":11,"column":1},"end":{"line":11,"column":1}},"children":[{"type":"paragraph","children":[{"type":"text","value":"Delete data","position":{"start":{"line":11,"column":1},"end":{"line":11,"column":1}},"key":"nL0QZjbr8q"}],"key":"ZA4eo2MBR5"}],"key":"jA8Ons2VUt"},{"type":"listItem","spread":true,"position":{"start":{"line":12,"column":1},"end":{"line":13,"column":1}},"children":[{"type":"paragraph","children":[{"type":"text","value":"Control access to data","position":{"start":{"line":12,"column":1},"end":{"line":12,"column":1}},"key":"UIFUIZTP1w"}],"key":"U2ojEhF2Im"}],"key":"jGWMmPLsOc"}],"key":"v8LrcfmhYG"},{"type":"paragraph","position":{"start":{"line":14,"column":1},"end":{"line":14,"column":1}},"children":[{"type":"text","value":"A simple SQL query looks like this:","position":{"start":{"line":14,"column":1},"end":{"line":14,"column":1}},"key":"bCPJNL8CdS"}],"key":"zKrwIFsrpK"},{"type":"code","lang":"sql","value":"SELECT *\nFROM Student;","position":{"start":{"line":16,"column":1},"end":{"line":19,"column":1}},"key":"iuzTGQhTcE"},{"type":"paragraph","position":{"start":{"line":21,"column":1},"end":{"line":21,"column":1}},"children":[{"type":"text","value":"This means: show all columns and rows from the ","position":{"start":{"line":21,"column":1},"end":{"line":21,"column":1}},"key":"yaqbK29nv0"},{"type":"inlineCode","value":"Student","position":{"start":{"line":21,"column":1},"end":{"line":21,"column":1}},"key":"gL4FFqZPkE"},{"type":"text","value":" table.","position":{"start":{"line":21,"column":1},"end":{"line":21,"column":1}},"key":"bWEMlLBfR2"}],"key":"wmAZMmU4qe"}],"key":"eNUZPfLpBB"},{"type":"block","kind":"notebook-content","children":[{"type":"heading","depth":2,"position":{"start":{"line":1,"column":1},"end":{"line":1,"column":1}},"children":[{"type":"text","value":"1.8 Why Structure Matters","position":{"start":{"line":1,"column":1},"end":{"line":1,"column":1}},"key":"YJADKgn6gb"}],"identifier":"id-1-8-why-structure-matters","label":"1.8 Why Structure Matters","html_id":"id-1-8-why-structure-matters","implicit":true,"key":"KqH7orBHKG"},{"type":"paragraph","position":{"start":{"line":3,"column":1},"end":{"line":3,"column":1}},"children":[{"type":"text","value":"Imagine storing all college data in one spreadsheet:","position":{"start":{"line":3,"column":1},"end":{"line":3,"column":1}},"key":"fZwpwhM3Ht"}],"key":"qB5UY2m0yt"},{"type":"table","position":{"start":{"line":5,"column":1},"end":{"line":9,"column":1}},"children":[{"type":"tableRow","position":{"start":{"line":5,"column":1},"end":{"line":5,"column":1}},"children":[{"type":"tableCell","header":true,"position":{"start":{"line":5,"column":1},"end":{"line":5,"column":1}},"children":[{"type":"text","value":"StudentName","position":{"start":{"line":5,"column":1},"end":{"line":5,"column":1}},"key":"KnY9wrKfKw"}],"key":"aJ6YjLk0GU"},{"type":"tableCell","header":true,"position":{"start":{"line":5,"column":1},"end":{"line":5,"column":1}},"children":[{"type":"text","value":"Major","position":{"start":{"line":5,"column":1},"end":{"line":5,"column":1}},"key":"Qx3yvuyi82"}],"key":"Q5u5UAdxOK"},{"type":"tableCell","header":true,"position":{"start":{"line":5,"column":1},"end":{"line":5,"column":1}},"children":[{"type":"text","value":"CourseName","position":{"start":{"line":5,"column":1},"end":{"line":5,"column":1}},"key":"SEUC294OsA"}],"key":"K3MOjpdpUF"},{"type":"tableCell","header":true,"position":{"start":{"line":5,"column":1},"end":{"line":5,"column":1}},"children":[{"type":"text","value":"Instructor","position":{"start":{"line":5,"column":1},"end":{"line":5,"column":1}},"key":"G9YNEKx7Zw"}],"key":"OhOAy5wJzw"},{"type":"tableCell","header":true,"position":{"start":{"line":5,"column":1},"end":{"line":5,"column":1}},"children":[{"type":"text","value":"Room","position":{"start":{"line":5,"column":1},"end":{"line":5,"column":1}},"key":"GaO4oHybtD"}],"key":"EycQpjqdgM"}],"key":"VzmNBRcUiY"},{"type":"tableRow","position":{"start":{"line":7,"column":1},"end":{"line":7,"column":1}},"children":[{"type":"tableCell","position":{"start":{"line":7,"column":1},"end":{"line":7,"column":1}},"children":[{"type":"text","value":"Maya Johnson","position":{"start":{"line":7,"column":1},"end":{"line":7,"column":1}},"key":"PZV2FApjD5"}],"key":"ttmIOsQQ2Y"},{"type":"tableCell","position":{"start":{"line":7,"column":1},"end":{"line":7,"column":1}},"children":[{"type":"text","value":"IST","position":{"start":{"line":7,"column":1},"end":{"line":7,"column":1}},"key":"Ewf0lAJJVG"}],"key":"dKMTjxTuhB"},{"type":"tableCell","position":{"start":{"line":7,"column":1},"end":{"line":7,"column":1}},"children":[{"type":"text","value":"Intro to Databases","position":{"start":{"line":7,"column":1},"end":{"line":7,"column":1}},"key":"w96hqZtni2"}],"key":"zA2hhrY6vt"},{"type":"tableCell","position":{"start":{"line":7,"column":1},"end":{"line":7,"column":1}},"children":[{"type":"text","value":"Dr. Lee","position":{"start":{"line":7,"column":1},"end":{"line":7,"column":1}},"key":"OQ5fBzi590"}],"key":"YgGbyj2lv1"},{"type":"tableCell","position":{"start":{"line":7,"column":1},"end":{"line":7,"column":1}},"children":[{"type":"text","value":"202","position":{"start":{"line":7,"column":1},"end":{"line":7,"column":1}},"key":"dRVjNWnaAs"}],"key":"eARKwElink"}],"key":"gW4eqFTkGW"},{"type":"tableRow","position":{"start":{"line":8,"column":1},"end":{"line":8,"column":1}},"children":[{"type":"tableCell","position":{"start":{"line":8,"column":1},"end":{"line":8,"column":1}},"children":[{"type":"text","value":"Carlos Rivera","position":{"start":{"line":8,"column":1},"end":{"line":8,"column":1}},"key":"AjuNF5MVZI"}],"key":"dXFzzGOUxt"},{"type":"tableCell","position":{"start":{"line":8,"column":1},"end":{"line":8,"column":1}},"children":[{"type":"text","value":"Business","position":{"start":{"line":8,"column":1},"end":{"line":8,"column":1}},"key":"zLaKpjfhIl"}],"key":"mCKUkHXael"},{"type":"tableCell","position":{"start":{"line":8,"column":1},"end":{"line":8,"column":1}},"children":[{"type":"text","value":"Intro to Databases","position":{"start":{"line":8,"column":1},"end":{"line":8,"column":1}},"key":"UUr9sMsddy"}],"key":"F0vsnyRqI7"},{"type":"tableCell","position":{"start":{"line":8,"column":1},"end":{"line":8,"column":1}},"children":[{"type":"text","value":"Dr. Lee","position":{"start":{"line":8,"column":1},"end":{"line":8,"column":1}},"key":"ZdYBI5WldI"}],"key":"uHITRTmMjw"},{"type":"tableCell","position":{"start":{"line":8,"column":1},"end":{"line":8,"column":1}},"children":[{"type":"text","value":"202","position":{"start":{"line":8,"column":1},"end":{"line":8,"column":1}},"key":"cQ8017YjYV"}],"key":"NUtomQcwmp"}],"key":"eJvYhQ98Lh"},{"type":"tableRow","position":{"start":{"line":9,"column":1},"end":{"line":9,"column":1}},"children":[{"type":"tableCell","position":{"start":{"line":9,"column":1},"end":{"line":9,"column":1}},"children":[{"type":"text","value":"Amina Patel","position":{"start":{"line":9,"column":1},"end":{"line":9,"column":1}},"key":"YpDuxSq0j8"}],"key":"biH3cg2sWI"},{"type":"tableCell","position":{"start":{"line":9,"column":1},"end":{"line":9,"column":1}},"children":[{"type":"text","value":"Engineering","position":{"start":{"line":9,"column":1},"end":{"line":9,"column":1}},"key":"YyyiBButSR"}],"key":"kXznGFWb04"},{"type":"tableCell","position":{"start":{"line":9,"column":1},"end":{"line":9,"column":1}},"children":[{"type":"text","value":"Web Development","position":{"start":{"line":9,"column":1},"end":{"line":9,"column":1}},"key":"ROBiiaSUdp"}],"key":"Ugkr8DRyb5"},{"type":"tableCell","position":{"start":{"line":9,"column":1},"end":{"line":9,"column":1}},"children":[{"type":"text","value":"Dr. Gomez","position":{"start":{"line":9,"column":1},"end":{"line":9,"column":1}},"key":"j5aPZTDlZF"}],"key":"tvSeroE4Sd"},{"type":"tableCell","position":{"start":{"line":9,"column":1},"end":{"line":9,"column":1}},"children":[{"type":"text","value":"118","position":{"start":{"line":9,"column":1},"end":{"line":9,"column":1}},"key":"xTdVKN6lSc"}],"key":"MeC459HGAg"}],"key":"aHourj5CsI"}],"key":"pTJIxIS56C"},{"type":"paragraph","position":{"start":{"line":11,"column":1},"end":{"line":11,"column":1}},"children":[{"type":"text","value":"This might work at first, but problems appear quickly:","position":{"start":{"line":11,"column":1},"end":{"line":11,"column":1}},"key":"M086mTLtgU"}],"key":"D3J0VFxPMU"},{"type":"list","ordered":false,"spread":false,"position":{"start":{"line":13,"column":1},"end":{"line":17,"column":1}},"children":[{"type":"listItem","spread":true,"position":{"start":{"line":13,"column":1},"end":{"line":13,"column":1}},"children":[{"type":"paragraph","children":[{"type":"text","value":"The instructor’s name may be repeated many times.","position":{"start":{"line":13,"column":1},"end":{"line":13,"column":1}},"key":"UkhYoje1q0"}],"key":"NjHWbwGMLw"}],"key":"TfJ1eC5UMS"},{"type":"listItem","spread":true,"position":{"start":{"line":14,"column":1},"end":{"line":14,"column":1}},"children":[{"type":"paragraph","children":[{"type":"text","value":"A room change might require updates in many rows.","position":{"start":{"line":14,"column":1},"end":{"line":14,"column":1}},"key":"plctjnPDiU"}],"key":"S5E0TuUlUL"}],"key":"qKQqphaFLs"},{"type":"listItem","spread":true,"position":{"start":{"line":15,"column":1},"end":{"line":15,"column":1}},"children":[{"type":"paragraph","children":[{"type":"text","value":"A student’s name could be typed differently in different places.","position":{"start":{"line":15,"column":1},"end":{"line":15,"column":1}},"key":"EejIVzz9ek"}],"key":"aBGTHqGCmc"}],"key":"l9ox744DRY"},{"type":"listItem","spread":true,"position":{"start":{"line":16,"column":1},"end":{"line":17,"column":1}},"children":[{"type":"paragraph","children":[{"type":"text","value":"It becomes difficult to track which students, courses, instructors, and rooms are truly separate things.","position":{"start":{"line":16,"column":1},"end":{"line":16,"column":1}},"key":"XSKSiJVl6a"}],"key":"IJwdMnovfa"}],"key":"IWGBhBluii"}],"key":"XROBaa0QgT"},{"type":"paragraph","position":{"start":{"line":18,"column":1},"end":{"line":18,"column":1}},"children":[{"type":"text","value":"A database helps solve these problems by organizing data into related tables.","position":{"start":{"line":18,"column":1},"end":{"line":18,"column":1}},"key":"JdfG4mXZpK"}],"key":"fJloIYSOjI"}],"key":"IRp8mdzDb3"},{"type":"block","kind":"notebook-content","children":[{"type":"heading","depth":2,"position":{"start":{"line":1,"column":1},"end":{"line":1,"column":1}},"children":[{"type":"text","value":"1.9 Common Types of Databases","position":{"start":{"line":1,"column":1},"end":{"line":1,"column":1}},"key":"cUi9pMbn3e"}],"identifier":"id-1-9-common-types-of-databases","label":"1.9 Common Types of Databases","html_id":"id-1-9-common-types-of-databases","implicit":true,"key":"l9w7HjJHzA"},{"type":"paragraph","position":{"start":{"line":3,"column":1},"end":{"line":3,"column":1}},"children":[{"type":"text","value":"Although this book focuses on relational databases, it is useful to know that there are several types of databases.","position":{"start":{"line":3,"column":1},"end":{"line":3,"column":1}},"key":"CMlDRFMdFg"}],"key":"CRLrjYsJQ2"},{"type":"table","position":{"start":{"line":5,"column":1},"end":{"line":11,"column":1}},"children":[{"type":"tableRow","position":{"start":{"line":5,"column":1},"end":{"line":5,"column":1}},"children":[{"type":"tableCell","header":true,"position":{"start":{"line":5,"column":1},"end":{"line":5,"column":1}},"children":[{"type":"text","value":"Type","position":{"start":{"line":5,"column":1},"end":{"line":5,"column":1}},"key":"o5dypIDlXd"}],"key":"xMhiQ0U423"},{"type":"tableCell","header":true,"position":{"start":{"line":5,"column":1},"end":{"line":5,"column":1}},"children":[{"type":"text","value":"Basic Idea","position":{"start":{"line":5,"column":1},"end":{"line":5,"column":1}},"key":"RMTw2fs0hC"}],"key":"KTo2sVoC4B"},{"type":"tableCell","header":true,"position":{"start":{"line":5,"column":1},"end":{"line":5,"column":1}},"children":[{"type":"text","value":"Example Use","position":{"start":{"line":5,"column":1},"end":{"line":5,"column":1}},"key":"vhhXzFWmc6"}],"key":"Zoe8sFVKTl"}],"key":"HCTV83y5oe"},{"type":"tableRow","position":{"start":{"line":7,"column":1},"end":{"line":7,"column":1}},"children":[{"type":"tableCell","position":{"start":{"line":7,"column":1},"end":{"line":7,"column":1}},"children":[{"type":"text","value":"Relational database","position":{"start":{"line":7,"column":1},"end":{"line":7,"column":1}},"key":"XWJDn8kH8Q"}],"key":"v5tsbu1JT9"},{"type":"tableCell","position":{"start":{"line":7,"column":1},"end":{"line":7,"column":1}},"children":[{"type":"text","value":"Data stored in related tables","position":{"start":{"line":7,"column":1},"end":{"line":7,"column":1}},"key":"bMURf4PF5Z"}],"key":"DkZSJJLmPa"},{"type":"tableCell","position":{"start":{"line":7,"column":1},"end":{"line":7,"column":1}},"children":[{"type":"text","value":"Student records, sales systems","position":{"start":{"line":7,"column":1},"end":{"line":7,"column":1}},"key":"nbudYjsIug"}],"key":"reAdaoUNy9"}],"key":"H9kNhM99Si"},{"type":"tableRow","position":{"start":{"line":8,"column":1},"end":{"line":8,"column":1}},"children":[{"type":"tableCell","position":{"start":{"line":8,"column":1},"end":{"line":8,"column":1}},"children":[{"type":"text","value":"Document database","position":{"start":{"line":8,"column":1},"end":{"line":8,"column":1}},"key":"TkrWZwaZAS"}],"key":"LeHXJMMsaK"},{"type":"tableCell","position":{"start":{"line":8,"column":1},"end":{"line":8,"column":1}},"children":[{"type":"text","value":"Data stored as flexible documents","position":{"start":{"line":8,"column":1},"end":{"line":8,"column":1}},"key":"GaZRkafrIe"}],"key":"lf23iKRf9F"},{"type":"tableCell","position":{"start":{"line":8,"column":1},"end":{"line":8,"column":1}},"children":[{"type":"text","value":"Web applications, product catalogs","position":{"start":{"line":8,"column":1},"end":{"line":8,"column":1}},"key":"bgRTpZVQ5O"}],"key":"LblAtqsqFZ"}],"key":"rx7F6uvdZp"},{"type":"tableRow","position":{"start":{"line":9,"column":1},"end":{"line":9,"column":1}},"children":[{"type":"tableCell","position":{"start":{"line":9,"column":1},"end":{"line":9,"column":1}},"children":[{"type":"text","value":"Graph database","position":{"start":{"line":9,"column":1},"end":{"line":9,"column":1}},"key":"MGA11cwWjJ"}],"key":"ZK94pF1VZP"},{"type":"tableCell","position":{"start":{"line":9,"column":1},"end":{"line":9,"column":1}},"children":[{"type":"text","value":"Data stored as nodes and relationships","position":{"start":{"line":9,"column":1},"end":{"line":9,"column":1}},"key":"zRCu1FdvJ6"}],"key":"plehKBdutp"},{"type":"tableCell","position":{"start":{"line":9,"column":1},"end":{"line":9,"column":1}},"children":[{"type":"text","value":"Social networks, recommendation systems","position":{"start":{"line":9,"column":1},"end":{"line":9,"column":1}},"key":"iaZGSpF2zN"}],"key":"vd82NxPN6U"}],"key":"u2XY0H5Sg7"},{"type":"tableRow","position":{"start":{"line":10,"column":1},"end":{"line":10,"column":1}},"children":[{"type":"tableCell","position":{"start":{"line":10,"column":1},"end":{"line":10,"column":1}},"children":[{"type":"text","value":"Key-value database","position":{"start":{"line":10,"column":1},"end":{"line":10,"column":1}},"key":"pBPvwuKi6V"}],"key":"r2ruT0CAAr"},{"type":"tableCell","position":{"start":{"line":10,"column":1},"end":{"line":10,"column":1}},"children":[{"type":"text","value":"Data stored as key-value pairs","position":{"start":{"line":10,"column":1},"end":{"line":10,"column":1}},"key":"ATXbKQ6sp3"}],"key":"JGUw57Jlth"},{"type":"tableCell","position":{"start":{"line":10,"column":1},"end":{"line":10,"column":1}},"children":[{"type":"text","value":"Caching, fast lookups","position":{"start":{"line":10,"column":1},"end":{"line":10,"column":1}},"key":"lmZEElXrG7"}],"key":"T6cchJE6Nq"}],"key":"FWjx7KpTDL"},{"type":"tableRow","position":{"start":{"line":11,"column":1},"end":{"line":11,"column":1}},"children":[{"type":"tableCell","position":{"start":{"line":11,"column":1},"end":{"line":11,"column":1}},"children":[{"type":"text","value":"Object-oriented database","position":{"start":{"line":11,"column":1},"end":{"line":11,"column":1}},"key":"bK16CK6JNw"}],"key":"K7IiG2ZtxA"},{"type":"tableCell","position":{"start":{"line":11,"column":1},"end":{"line":11,"column":1}},"children":[{"type":"text","value":"Data stored as objects","position":{"start":{"line":11,"column":1},"end":{"line":11,"column":1}},"key":"zYhSOigg0L"}],"key":"Rx1kG6VWxL"},{"type":"tableCell","position":{"start":{"line":11,"column":1},"end":{"line":11,"column":1}},"children":[{"type":"text","value":"Specialized software systems","position":{"start":{"line":11,"column":1},"end":{"line":11,"column":1}},"key":"LD1dNcq8PU"}],"key":"ATM4w4uNQn"}],"key":"XOxOpdQrDb"}],"key":"mtUQ977dvh"},{"type":"paragraph","position":{"start":{"line":13,"column":1},"end":{"line":13,"column":1}},"children":[{"type":"text","value":"Relational databases remain widely used because they are powerful, structured, and supported by SQL.","position":{"start":{"line":13,"column":1},"end":{"line":13,"column":1}},"key":"WTrqPpjQme"}],"key":"RebPk7d5hX"}],"key":"k5L9p3ZVcw"},{"type":"block","kind":"notebook-content","children":[{"type":"heading","depth":2,"position":{"start":{"line":1,"column":1},"end":{"line":1,"column":1}},"children":[{"type":"text","value":"1.10 Key Terms","position":{"start":{"line":1,"column":1},"end":{"line":1,"column":1}},"key":"im7KwSLkbf"}],"identifier":"id-1-10-key-terms","label":"1.10 Key Terms","html_id":"id-1-10-key-terms","implicit":true,"key":"aHMyHFP6bn"},{"type":"table","position":{"start":{"line":3,"column":1},"end":{"line":14,"column":1}},"children":[{"type":"tableRow","position":{"start":{"line":3,"column":1},"end":{"line":3,"column":1}},"children":[{"type":"tableCell","header":true,"position":{"start":{"line":3,"column":1},"end":{"line":3,"column":1}},"children":[{"type":"text","value":"Term","position":{"start":{"line":3,"column":1},"end":{"line":3,"column":1}},"key":"eHeC2GBXkT"}],"key":"JMIZpQrDNY"},{"type":"tableCell","header":true,"position":{"start":{"line":3,"column":1},"end":{"line":3,"column":1}},"children":[{"type":"text","value":"Meaning","position":{"start":{"line":3,"column":1},"end":{"line":3,"column":1}},"key":"IENWjXfvAx"}],"key":"cI0GIzG5ol"}],"key":"VEqbbv9OC9"},{"type":"tableRow","position":{"start":{"line":5,"column":1},"end":{"line":5,"column":1}},"children":[{"type":"tableCell","position":{"start":{"line":5,"column":1},"end":{"line":5,"column":1}},"children":[{"type":"text","value":"Data","position":{"start":{"line":5,"column":1},"end":{"line":5,"column":1}},"key":"Pe21vrkl4Z"}],"key":"ceiWSlhCND"},{"type":"tableCell","position":{"start":{"line":5,"column":1},"end":{"line":5,"column":1}},"children":[{"type":"text","value":"Raw facts or values","position":{"start":{"line":5,"column":1},"end":{"line":5,"column":1}},"key":"Vmiodu4mST"}],"key":"yozwakjLdm"}],"key":"OkWBFO4QKZ"},{"type":"tableRow","position":{"start":{"line":6,"column":1},"end":{"line":6,"column":1}},"children":[{"type":"tableCell","position":{"start":{"line":6,"column":1},"end":{"line":6,"column":1}},"children":[{"type":"text","value":"Information","position":{"start":{"line":6,"column":1},"end":{"line":6,"column":1}},"key":"bFuZTnyWQS"}],"key":"vS1yZbNWmt"},{"type":"tableCell","position":{"start":{"line":6,"column":1},"end":{"line":6,"column":1}},"children":[{"type":"text","value":"Data organized into a meaningful form","position":{"start":{"line":6,"column":1},"end":{"line":6,"column":1}},"key":"mRulTi5XeI"}],"key":"InR9QJP4w2"}],"key":"r3seDxTBsR"},{"type":"tableRow","position":{"start":{"line":7,"column":1},"end":{"line":7,"column":1}},"children":[{"type":"tableCell","position":{"start":{"line":7,"column":1},"end":{"line":7,"column":1}},"children":[{"type":"text","value":"Database","position":{"start":{"line":7,"column":1},"end":{"line":7,"column":1}},"key":"EPW6XdMi9Q"}],"key":"t0ZR7gNTCc"},{"type":"tableCell","position":{"start":{"line":7,"column":1},"end":{"line":7,"column":1}},"children":[{"type":"text","value":"Organized collection of related data","position":{"start":{"line":7,"column":1},"end":{"line":7,"column":1}},"key":"qmXeOx3ArI"}],"key":"Mh0yQKgeiw"}],"key":"MPL05yhYZc"},{"type":"tableRow","position":{"start":{"line":8,"column":1},"end":{"line":8,"column":1}},"children":[{"type":"tableCell","position":{"start":{"line":8,"column":1},"end":{"line":8,"column":1}},"children":[{"type":"text","value":"DBMS","position":{"start":{"line":8,"column":1},"end":{"line":8,"column":1}},"key":"nQbJsonWHH"}],"key":"RPSjsyMna1"},{"type":"tableCell","position":{"start":{"line":8,"column":1},"end":{"line":8,"column":1}},"children":[{"type":"text","value":"Software used to manage a database","position":{"start":{"line":8,"column":1},"end":{"line":8,"column":1}},"key":"sWZQz0ERgE"}],"key":"kMTO47l7uZ"}],"key":"JOo8ewO9Ob"},{"type":"tableRow","position":{"start":{"line":9,"column":1},"end":{"line":9,"column":1}},"children":[{"type":"tableCell","position":{"start":{"line":9,"column":1},"end":{"line":9,"column":1}},"children":[{"type":"text","value":"Table","position":{"start":{"line":9,"column":1},"end":{"line":9,"column":1}},"key":"twsaWenLcH"}],"key":"zXMeYMxfyP"},{"type":"tableCell","position":{"start":{"line":9,"column":1},"end":{"line":9,"column":1}},"children":[{"type":"text","value":"Structure that stores data in rows and columns","position":{"start":{"line":9,"column":1},"end":{"line":9,"column":1}},"key":"n30Rns2eTV"}],"key":"uxuTlzLWpl"}],"key":"gMKjDxQbuU"},{"type":"tableRow","position":{"start":{"line":10,"column":1},"end":{"line":10,"column":1}},"children":[{"type":"tableCell","position":{"start":{"line":10,"column":1},"end":{"line":10,"column":1}},"children":[{"type":"text","value":"Row","position":{"start":{"line":10,"column":1},"end":{"line":10,"column":1}},"key":"fKqbUCyrAl"}],"key":"w3QNrcWbba"},{"type":"tableCell","position":{"start":{"line":10,"column":1},"end":{"line":10,"column":1}},"children":[{"type":"text","value":"A single record in a table","position":{"start":{"line":10,"column":1},"end":{"line":10,"column":1}},"key":"sRAebYYxu3"}],"key":"SjOGZn3uvs"}],"key":"mJwRZdpepd"},{"type":"tableRow","position":{"start":{"line":11,"column":1},"end":{"line":11,"column":1}},"children":[{"type":"tableCell","position":{"start":{"line":11,"column":1},"end":{"line":11,"column":1}},"children":[{"type":"text","value":"Column","position":{"start":{"line":11,"column":1},"end":{"line":11,"column":1}},"key":"B3V9ja48Vh"}],"key":"btpNc52LC0"},{"type":"tableCell","position":{"start":{"line":11,"column":1},"end":{"line":11,"column":1}},"children":[{"type":"text","value":"A field or attribute in a table","position":{"start":{"line":11,"column":1},"end":{"line":11,"column":1}},"key":"JzlLOpDnsr"}],"key":"kNRgQRf4Aw"}],"key":"oT9ERfvTaq"},{"type":"tableRow","position":{"start":{"line":12,"column":1},"end":{"line":12,"column":1}},"children":[{"type":"tableCell","position":{"start":{"line":12,"column":1},"end":{"line":12,"column":1}},"children":[{"type":"text","value":"SQL","position":{"start":{"line":12,"column":1},"end":{"line":12,"column":1}},"key":"oPGKG3buYO"}],"key":"Ve5QY6CYlm"},{"type":"tableCell","position":{"start":{"line":12,"column":1},"end":{"line":12,"column":1}},"children":[{"type":"text","value":"Language used to interact with relational databases","position":{"start":{"line":12,"column":1},"end":{"line":12,"column":1}},"key":"tv3n6fXnjp"}],"key":"kEWLwaNK2U"}],"key":"auFPKAXkrK"},{"type":"tableRow","position":{"start":{"line":13,"column":1},"end":{"line":13,"column":1}},"children":[{"type":"tableCell","position":{"start":{"line":13,"column":1},"end":{"line":13,"column":1}},"children":[{"type":"text","value":"Query","position":{"start":{"line":13,"column":1},"end":{"line":13,"column":1}},"key":"b9NagyEWmX"}],"key":"eyxVFWBg23"},{"type":"tableCell","position":{"start":{"line":13,"column":1},"end":{"line":13,"column":1}},"children":[{"type":"text","value":"A request for data from a database","position":{"start":{"line":13,"column":1},"end":{"line":13,"column":1}},"key":"JZ4cLQ1Xtu"}],"key":"ZNOzZ7cZsq"}],"key":"mZ4wNEBm2w"},{"type":"tableRow","position":{"start":{"line":14,"column":1},"end":{"line":14,"column":1}},"children":[{"type":"tableCell","position":{"start":{"line":14,"column":1},"end":{"line":14,"column":1}},"children":[{"type":"text","value":"Primary key","position":{"start":{"line":14,"column":1},"end":{"line":14,"column":1}},"key":"Raojjx3bm9"}],"key":"mwxYDLkunc"},{"type":"tableCell","position":{"start":{"line":14,"column":1},"end":{"line":14,"column":1}},"children":[{"type":"text","value":"A column or set of columns that uniquely identifies a row","position":{"start":{"line":14,"column":1},"end":{"line":14,"column":1}},"key":"poCB0TuE1V"}],"key":"R8OGEhUEcw"}],"key":"pvtzR0Lk4w"}],"key":"C2IclSc9EU"}],"key":"TSAGLDMViY"},{"type":"block","kind":"notebook-content","children":[{"type":"heading","depth":2,"position":{"start":{"line":1,"column":1},"end":{"line":1,"column":1}},"children":[{"type":"text","value":"1.18 Check Your Understanding","position":{"start":{"line":1,"column":1},"end":{"line":1,"column":1}},"key":"e2al3egEJ6"}],"identifier":"id-1-18-check-your-understanding","label":"1.18 Check Your Understanding","html_id":"id-1-18-check-your-understanding","implicit":true,"key":"uMC30Rx7up"},{"type":"paragraph","position":{"start":{"line":3,"column":1},"end":{"line":3,"column":1}},"children":[{"type":"text","value":"Answer the following questions in your own words.","position":{"start":{"line":3,"column":1},"end":{"line":3,"column":1}},"key":"p6hxyS8vQ4"}],"key":"tmgjtAhkMk"},{"type":"list","ordered":true,"start":1,"spread":false,"position":{"start":{"line":5,"column":1},"end":{"line":12,"column":1}},"children":[{"type":"listItem","spread":true,"position":{"start":{"line":5,"column":1},"end":{"line":5,"column":1}},"children":[{"type":"paragraph","children":[{"type":"text","value":"What is a database?","position":{"start":{"line":5,"column":1},"end":{"line":5,"column":1}},"key":"ojHJXTDBGb"}],"key":"TqIjHq1qWI"}],"key":"tNj03NTDlv"},{"type":"listItem","spread":true,"position":{"start":{"line":6,"column":1},"end":{"line":6,"column":1}},"children":[{"type":"paragraph","children":[{"type":"text","value":"What is the difference between data and information?","position":{"start":{"line":6,"column":1},"end":{"line":6,"column":1}},"key":"b8Y173dm4h"}],"key":"A5OUCBMeQw"}],"key":"xC7E488W2f"},{"type":"listItem","spread":true,"position":{"start":{"line":7,"column":1},"end":{"line":7,"column":1}},"children":[{"type":"paragraph","children":[{"type":"text","value":"What is a DBMS?","position":{"start":{"line":7,"column":1},"end":{"line":7,"column":1}},"key":"UnupcjODvz"}],"key":"l6x2kTZ4ft"}],"key":"NrFrRD9e6U"},{"type":"listItem","spread":true,"position":{"start":{"line":8,"column":1},"end":{"line":8,"column":1}},"children":[{"type":"paragraph","children":[{"type":"text","value":"Why might a database be better than a spreadsheet for an organization?","position":{"start":{"line":8,"column":1},"end":{"line":8,"column":1}},"key":"lf8XbxbJXl"}],"key":"iJhJGawbBx"}],"key":"eIqMY7z4BA"},{"type":"listItem","spread":true,"position":{"start":{"line":9,"column":1},"end":{"line":9,"column":1}},"children":[{"type":"paragraph","children":[{"type":"text","value":"What is SQL used for?","position":{"start":{"line":9,"column":1},"end":{"line":9,"column":1}},"key":"FHZGGMKOL0"}],"key":"YmRWXjZkFV"}],"key":"u2X35wfUmh"},{"type":"listItem","spread":true,"position":{"start":{"line":10,"column":1},"end":{"line":10,"column":1}},"children":[{"type":"paragraph","children":[{"type":"text","value":"In a table, what is the difference between a row and a column?","position":{"start":{"line":10,"column":1},"end":{"line":10,"column":1}},"key":"u0sOvuIeZi"}],"key":"va5KAuxNmb"}],"key":"RfcGWGmbk0"},{"type":"listItem","spread":true,"position":{"start":{"line":11,"column":1},"end":{"line":12,"column":1}},"children":[{"type":"paragraph","children":[{"type":"text","value":"What question do you think the following SQL query answers?","position":{"start":{"line":11,"column":1},"end":{"line":11,"column":1}},"key":"zUzbDYwLLM"}],"key":"q7fElmERpf"}],"key":"ZwvLU8qVBs"}],"key":"QRFLceFbw2"},{"type":"code","lang":"sql","value":"SELECT Major, COUNT(*)\nFROM Student\nGROUP BY Major;","position":{"start":{"line":13,"column":1},"end":{"line":17,"column":1}},"key":"jJOZT3Lrk6"}],"key":"iB2dXNKcsi"},{"type":"block","kind":"notebook-content","children":[{"type":"heading","depth":2,"position":{"start":{"line":1,"column":1},"end":{"line":1,"column":1}},"children":[{"type":"text","value":"1.19 Chapter Summary","position":{"start":{"line":1,"column":1},"end":{"line":1,"column":1}},"key":"ci0uoO26eE"}],"identifier":"id-1-19-chapter-summary","label":"1.19 Chapter Summary","html_id":"id-1-19-chapter-summary","implicit":true,"key":"Dr3IBoqhtV"},{"type":"paragraph","position":{"start":{"line":3,"column":1},"end":{"line":3,"column":1}},"children":[{"type":"text","value":"In this chapter, you learned that a database is an organized collection of related data. Databases are used across organizations to store, manage, and retrieve data efficiently.","position":{"start":{"line":3,"column":1},"end":{"line":3,"column":1}},"key":"QaiErLpVqt"}],"key":"xdTNRfiGx1"},{"type":"paragraph","position":{"start":{"line":5,"column":1},"end":{"line":5,"column":1}},"children":[{"type":"text","value":"You also learned that:","position":{"start":{"line":5,"column":1},"end":{"line":5,"column":1}},"key":"jLpDJh5nIn"}],"key":"oPPIzsgZoa"},{"type":"list","ordered":false,"spread":false,"position":{"start":{"line":7,"column":1},"end":{"line":13,"column":1}},"children":[{"type":"listItem","spread":true,"position":{"start":{"line":7,"column":1},"end":{"line":7,"column":1}},"children":[{"type":"paragraph","children":[{"type":"text","value":"Data are raw facts.","position":{"start":{"line":7,"column":1},"end":{"line":7,"column":1}},"key":"SbLqKcgVjJ"}],"key":"FnRVeGo5k9"}],"key":"ieUeSM16Xh"},{"type":"listItem","spread":true,"position":{"start":{"line":8,"column":1},"end":{"line":8,"column":1}},"children":[{"type":"paragraph","children":[{"type":"text","value":"Information is data made meaningful.","position":{"start":{"line":8,"column":1},"end":{"line":8,"column":1}},"key":"QZYFwJUBAb"}],"key":"OG8kRSLtlW"}],"key":"cbfIDjtOGC"},{"type":"listItem","spread":true,"position":{"start":{"line":9,"column":1},"end":{"line":9,"column":1}},"children":[{"type":"paragraph","children":[{"type":"text","value":"A DBMS manages databases.","position":{"start":{"line":9,"column":1},"end":{"line":9,"column":1}},"key":"cNw1I6eTni"}],"key":"gvZI8UDZBY"}],"key":"bq9BY4Hzph"},{"type":"listItem","spread":true,"position":{"start":{"line":10,"column":1},"end":{"line":10,"column":1}},"children":[{"type":"paragraph","children":[{"type":"text","value":"Relational databases organize data into tables.","position":{"start":{"line":10,"column":1},"end":{"line":10,"column":1}},"key":"h5WwrxLKij"}],"key":"v04pc53W56"}],"key":"w7i2tybI4w"},{"type":"listItem","spread":true,"position":{"start":{"line":11,"column":1},"end":{"line":11,"column":1}},"children":[{"type":"paragraph","children":[{"type":"text","value":"Tables contain rows and columns.","position":{"start":{"line":11,"column":1},"end":{"line":11,"column":1}},"key":"ob14mIpFK5"}],"key":"lCgrHHuMvH"}],"key":"FbCBFwYu5C"},{"type":"listItem","spread":true,"position":{"start":{"line":12,"column":1},"end":{"line":13,"column":1}},"children":[{"type":"paragraph","children":[{"type":"text","value":"SQL is used to communicate with relational databases.","position":{"start":{"line":12,"column":1},"end":{"line":12,"column":1}},"key":"dcoOkOZNcW"}],"key":"ItiNm3HdsP"}],"key":"RVajVLzfJL"}],"key":"o7akwpcwSE"},{"type":"paragraph","position":{"start":{"line":14,"column":1},"end":{"line":14,"column":1}},"children":[{"type":"text","value":"In the next chapter, we will begin looking more closely at how data is modeled before it becomes a database.","position":{"start":{"line":14,"column":1},"end":{"line":14,"column":1}},"key":"pMAKEL06QE"}],"key":"TxO66llbAX"}],"key":"sam9l0IMs6"}],"key":"kEQRkaEh2C"},"references":{"cite":{"order":[],"data":{}}}}